autovix/__init__.py
autovix/git_cloner.py
autovix/utils.py
autovix-0.1.3.dist-info/METADATA
autovix-0.1.3.dist-info/WHEEL
autovix-0.1.3.dist-info/top_level.txt
autovix-0.1.3.dist-info/RECORD
