Metadata-Version: 2.4
Name: autovix
Version: 0.1.3
Summary: Utility for automated Git cloning and app launching (React/FastAPI)
Home-page: https://github.com/VenkeyReddy123/autiovix.git
Author: VenkateswarluReddyLekkala
Author-email: venkateswarlureddy647@gmail.com
Classifier: Programming Language :: Python :: 3
Classifier: License :: OSI Approved :: MIT License
Classifier: Operating System :: OS Independent
Requires-Python: >=3.7
Requires-Dist: fastapi
Requires-Dist: uvicorn
Dynamic: author
Dynamic: author-email
Dynamic: classifier
Dynamic: description
Dynamic: description-content-type
Dynamic: home-page
Dynamic: requires-dist
Dynamic: requires-python
Dynamic: summary
